amapy_pluggy/__init__.py
amapy_pluggy/plugin/__init__.py
amapy_pluggy/plugin/asset_object.py
amapy_pluggy/plugin/object_content.py
amapy_pluggy/plugin/object_manager.py
amapy_pluggy/plugin/plugin_manager.py
amapy_pluggy/plugin/specs.py
amapy_pluggy/plugin/storage_manager.py
amapy_pluggy/plugin/tests/__init__.py
amapy_pluggy/plugin/tests/test_plugin_manager.py
amapy_pluggy/plugin/tests/test_storage_manager.py
amapy_pluggy/storage/__init__.py
amapy_pluggy/storage/asset_storage.py
amapy_pluggy/storage/mount_config.py
amapy_pluggy/storage/storage_credentials.py
amapy_pluggy/storage/storage_factory.py
amapy_pluggy/storage/storage_utils.py
amapy_pluggy/storage/blob/__init__.py
amapy_pluggy/storage/blob/blob_data.py
amapy_pluggy/storage/blob/storage_data.py
amapy_pluggy/storage/tests/__init__.py
amapy_pluggy/storage/tests/test_mount_config.py
amapy_pluggy/storage/tests/test_storage_credentials.py
amapy_pluggy/storage/tests/test_storage_factory.py
amapy_pluggy/storage/tests/test_storage_utils.py
amapy_pluggy/storage/transporter/__init__.py
amapy_pluggy/storage/transporter/transport_resource.py
amapy_pluggy/storage/transporter/transporter.py
amapy_pluggy/storage/transporter/tests/__init__.py
amapy_pluggy/storage/transporter/tests/test_transporter.py
amapy_pluggy/storage/urls/__init__.py
amapy_pluggy/storage/urls/blob_store_url.py
amapy_pluggy/storage/urls/storage_url.py
amapy_pluggy/storage/urls/tests/__init__.py
amapy_pluggy/storage/urls/tests/test_blob_store_url.py
amapy_pluggy-1.0.1.dist-info/METADATA
amapy_pluggy-1.0.1.dist-info/WHEEL
amapy_pluggy-1.0.1.dist-info/top_level.txt
amapy_pluggy-1.0.1.dist-info/RECORD
