Metadata-Version: 2.1
Name: amapy-pluggy
Version: 1.0.1
Summary: A Plugin handler for ama project.
Author-email: Swarup Mahanti <swarup.mahanti@roche.com>
Maintainer-email: Swarup Mahanti <swarup.mahanti@roche.com>
License: Copyright (c) 2024 Roche Diagnostics Computation Science & Informatics
Requires-Python: <3.11,>=3.10
Requires-Dist: amapy-utils==1.*
Requires-Dist: pluggy==1.5.*
